{
	"parent": "trollkin_v3:trollkin/root",
	"display": {
		"icon": {
			"id": "minecraft:soul_sand"
		},
		"title": {
			"translate": "trollkin_v3.advancement.soul_crafter"
		},
		"description": {
			"translate": "trollkin_v3.advancement.soul_crafter.desc"
		},
		"frame": "challenge"
	},
	"criteria": {
		"sand": {
			"trigger": "minecraft:recipe_crafted",
			"conditions": {
				"recipe_id": "trollkin_v3:soul_sand"
			}
		},
		"soil": {
			"trigger": "minecraft:recipe_crafted",
			"conditions": {
				"recipe_id": "trollkin_v3:soul_soil"
			}
		}
	},
	"requirements": [
		["sand", "soil"]
	]
}
